{
  "slug": "vocal-new-product-launch-magic-18000-smooth-curve-smart-display",
  "en": {
    "title": "Company News - VOZOL",
    "description": "Latest news and updates from VOZOL company",
    "content": "<div class=\"container\">\n  <h1 class=\"text-2xl font-bold mb-4\">Company News</h1>\n  <div class=\"grid grid-cols-1 md:grid-cols-2 lg:grid-cols-3 gap-6\">\n    <div class=\"bg-white rounded-lg shadow p-4\">\n      <h2 class=\"text-xl font-semibold mb-2\">Latest Product Launch</h2>\n      <p class=\"text-gray-700\">VOZOL announces its newest product line with innovative features.</p>\n      <div class=\"mt-4 text-sm text-gray-500\">Posted on June 15, 2023</div>\n    </div>\n    <div class=\"bg-white rounded-lg shadow p-4\">\n      <h2 class=\"text-xl font-semibold mb-2\">Industry Recognition</h2>\n      <p class=\"text-gray-700\">VOZOL receives prestigious award for technological innovation.</p>\n      <div class=\"mt-4 text-sm text-gray-500\">Posted on May 28, 2023</div>\n    </div>\n    <div class=\"bg-white rounded-lg shadow p-4\">\n      <h2 class=\"text-xl font-semibold mb-2\">Partnership Announcement</h2>\n      <p class=\"text-gray-700\">VOZOL partners with leading tech company to expand market reach.</p>\n      <div class=\"mt-4 text-sm text-gray-500\">Posted on April 10, 2023</div>\n    </div>\n  </div>\n</div>"
  },
  "es": {
    "title": "Noticias de la Empresa - VOZOL",
    "description": "Últimas noticias y actualizaciones de la empresa VOZOL.",
    "content": "<div class=\"container\">\n  <h1 class=\"text-2xl font-bold mb-4\">Noticias de la Empresa</h1>\n  <div class=\"grid grid-cols-1 md:grid-cols-2 lg:grid-cols-3 gap-6\">\n    <div class=\"bg-white rounded-lg shadow p-4\">\n      <h2 class=\"text-xl font-semibold mb-2\">Lanzamiento del Último Producto</h2>\n      <p class=\"text-gray-700\">VOZOL anuncia su nueva línea de productos con características innovadoras.</p>\n      <div class=\"mt-4 text-sm text-gray-500\">Publicado el 15 de junio de 2023</div>\n    </div>\n    <div class=\"bg-white rounded-lg shadow p-4\">\n      <h2 class=\"text-xl font-semibold mb-2\">Reconocimiento de la Industria</h2>\n      <p class=\"text-gray-700\">VOZOL recibe un prestigioso premio por innovación tecnológica.</p>\n      <div class=\"mt-4 text-sm text-gray-500\">Publicado el 28 de mayo de 2023</div>\n    </div>\n    <div class=\"bg-white rounded-lg shadow p-4\">\n      <h2 class=\"text-xl font-semibold mb-2\">Anuncio de Alianza</h2>\n      <p class=\"text-gray-700\">VOZOL se asocia con una empresa líder en tecnología para expandir su alcance en el mercado.</p>\n      <div class=\"mt-4 text-sm text-gray-500\">Publicado el 10 de abril de 2023</div>\n    </div>\n  </div>\n</div>"
  },
  "fr": {
    "title": "Actualités de l'Entreprise - VOZOL",
    "description": "Dernières nouvelles et mises à jour de la société VOZOL",
    "content": "<div class=\"container\">\n  <h1 class=\"text-2xl font-bold mb-4\">Actualités de l'Entreprise</h1>\n  <div class=\"grid grid-cols-1 md:grid-cols-2 lg:grid-cols-3 gap-6\">\n    <div class=\"bg-white rounded-lg shadow p-4\">\n      <h2 class=\"text-xl font-semibold mb-2\">Nouveau Produit Lancé</h2>\n      <p class=\"text-gray-700\">VOZOL annonce sa nouvelle gamme de produits avec des fonctionnalités innovantes.</p>\n      <div class=\"mt-4 text-sm text-gray-500\">Publié le 15 juin 2023</div>\n    </div>\n    <div class=\"bg-white rounded-lg shadow p-4\">\n      <h2 class=\"text-xl font-semibold mb-2\">Reconnaissance de l'Industrie</h2>\n      <p class=\"text-gray-700\">VOZOL reçoit un prix prestigieux pour son innovation technologique.</p>\n      <div class=\"mt-4 text-sm text-gray-500\">Publié le 28 mai 2023</div>\n    </div>\n    <div class=\"bg-white rounded-lg shadow p-4\">\n      <h2 class=\"text-xl font-semibold mb-2\">Annonce de Partenariat</h2>\n      <p class=\"text-gray-700\">VOZOL s'associe à une entreprise technologique leader pour étendre sa présence sur le marché.</p>\n      <div class=\"mt-4 text-sm text-gray-500\">Publié le 10 avril 2023</div>\n    </div>\n  </div>\n</div>"
  },
  "de": {
    "title": "Firmennachrichten - VOZOL",
    "description": "Aktuelle Neuigkeiten und Updates von der Firma VOZOL",
    "content": "<div class=\"container\">\n  <h1 class=\"text-2xl font-bold mb-4\">Unternehmensnachrichten</h1>\n  <div class=\"grid grid-cols-1 md:grid-cols-2 lg:grid-cols-3 gap-6\">\n    <div class=\"bg-white rounded-lg shadow p-4\">\n      <h2 class=\"text-xl font-semibold mb-2\">Neueste Produkteinführung</h2>\n      <p class=\"text-gray-700\">VOZOL kündigt seine neueste Produktlinie mit innovativen Funktionen an.</p>\n      <div class=\"mt-4 text-sm text-gray-500\">Veröffentlicht am 15. Juni 2023</div>\n    </div>\n    <div class=\"bg-white rounded-lg shadow p-4\">\n      <h2 class=\"text-xl font-semibold mb-2\">Branchenauszeichnung</h2>\n      <p class=\"text-gray-700\">VOZOL erhält renommierten Preis für technologische Innovation.</p>\n      <div class=\"mt-4 text-sm text-gray-500\">Veröffentlicht am 28. Mai 2023</div>\n    </div>\n    <div class=\"bg-white rounded-lg shadow p-4\">\n      <h2 class=\"text-xl font-semibold mb-2\">Partnerschaftsanzeige</h2>\n      <p class=\"text-gray-700\">VOZOL geht Partnerschaft mit führendem Technologieunternehmen ein, um die Marktreichweite zu erweitern.</p>\n      <div class=\"mt-4 text-sm text-gray-500\">Veröffentlicht am 10. April 2023</div>\n    </div>\n  </div>\n</div>"
  },
  "it": {
    "title": "企业新闻 - VOZOL",
    "description": "Ultime notizie e aggiornamenti dall'azienda VOZOL",
    "content": "<div class=\"container\">\n  <h1 class=\"text-2xl font-bold mb-4\">Notizie Aziendali</h1>\n  <div class=\"grid grid-cols-1 md:grid-cols-2 lg:grid-cols-3 gap-6\">\n    <div class=\"bg-white rounded-lg shadow p-4\">\n      <h2 class=\"text-xl font-semibold mb-2\">Ultimo Lancio di Prodotto</h2>\n      <p class=\"text-gray-700\">VOZOL annuncia la sua nuova linea di prodotti con caratteristiche innovative.</p>\n      <div class=\"mt-4 text-sm text-gray-500\">Pubblicato il 15 giugno 2023</div>\n    </div>\n    <div class=\"bg-white rounded-lg shadow p-4\">\n      <h2 class=\"text-xl font-semibold mb-2\">Riconoscimento del Settore</h2>\n      <p class=\"text-gray-700\">VOZOL riceve un prestigioso premio per l'innovazione tecnologica.</p>\n      <div class=\"mt-4 text-sm text-gray-500\">Pubblicato il 28 maggio 2023</div>\n    </div>\n    <div class=\"bg-white rounded-lg shadow p-4\">\n      <h2 class=\"text-xl font-semibold mb-2\">Annuncio di Partnership</h2>\n      <p class=\"text-gray-700\">VOZOL collabora con un'azienda tecnologica leader per espandere la propria presenza sul mercato.</p>\n      <div class=\"mt-4 text-sm text-gray-500\">Pubblicato il 10 aprile 2023</div>\n    </div>\n  </div>\n</div>"
  },
  "pt": {
    "title": "Notícias da Empresa - VOZOL",
    "description": "Últimas notícias e atualizações da empresa VOZOL",
    "content": "```html\n<div class=\"container\">\n  <h1 class=\"text-2xl font-bold mb-4\">Notícias da Empresa</h1>\n  <div class=\"grid grid-cols-1 md:grid-cols-2 lg:grid-cols-3 gap-6\">\n    <div class=\"bg-white rounded-lg shadow p-4\">\n      <h2 class=\"text-xl font-semibold mb-2\">Lançamento do Produto Mais Recente</h2>\n      <p class=\"text-gray-700\">A VOZOL anuncia sua nova linha de produtos com recursos inovadores.</p>\n      <div class=\"mt-4 text-sm text-gray-500\">Publicado em 15 de junho de 2023</div>\n    </div>\n    <div class=\"bg-white rounded-lg shadow p-4\">\n      <h2 class=\"text-xl font-semibold mb-2\">Reconhecimento do Setor</h2>\n      <p class=\"text-gray-700\">A VOZOL recebe prêmio prestigiado por inovação tecnológica.</p>\n      <div class=\"mt-4 text-sm text-gray-500\">Publicado em 28 de maio de 2023</div>\n    </div>\n    <div class=\"bg-white rounded-lg shadow p-4\">\n      <h2 class=\"text-xl font-semibold mb-2\">Anúncio de Parceria</h2>\n      <p class=\"text-gray-700\">A VOZOL estabelece parceria com empresa líder em tecnologia para expandir seu alcance no mercado.</p>\n      <div class=\"mt-4 text-sm text-gray-500\">Publicado em 10 de abril de 2023</div>\n    </div>\n  </div>\n</div>\n```"
  },
  "ru": {
    "title": "Новости компании - VOZOL",
    "description": "Последние новости и обновления от компании VOZOL",
    "content": "<div class=\"container\">\n  <h1 class=\"text-2xl font-bold mb-4\">Новости компании</h1>\n  <div class=\"grid grid-cols-1 md:grid-cols-2 lg:grid-cols-3 gap-6\">\n    <div class=\"bg-white rounded-lg shadow p-4\">\n      <h2 class=\"text-xl font-semibold mb-2\">Новый продукт</h2>\n      <p class=\"text-gray-700\">VOZOL представляет новую линейку продуктов с инновационными функциями.</p>\n      <div class=\"mt-4 text-sm text-gray-500\">Опубликовано 15 июня 2023</div>\n    </div>\n    <div class=\"bg-white rounded-lg shadow p-4\">\n      <h2 class=\"text-xl font-semibold mb-2\">Признание в отрасли</h2>\n      <p class=\"text-gray-700\">VOZOL получает престижную награду за технологические инновации.</p>\n      <div class=\"mt-4 text-sm text-gray-500\">Опубликовано 28 мая 2023</div>\n    </div>\n    <div class=\"bg-white rounded-lg shadow p-4\">\n      <h2 class=\"text-xl font-semibold mb-2\">Новое партнёрство</h2>\n      <p class=\"text-gray-700\">VOZOL сотрудничает с ведущей технологической компанией для расширения рынка.</p>\n      <div class=\"mt-4 text-sm text-gray-500\">Опубликовано 10 апреля 2023</div>\n    </div>\n  </div>\n</div>"
  },
  "pl": {
    "title": "Aktualności Firmowe - VOZOL",
    "description": "Najnowsze wiadomości i aktualizacje od firmy VOZOL",
    "content": "<div class=\"container\">\n  <h1 class=\"text-2xl font-bold mb-4\">Aktualności Firmy</h1>\n  <div class=\"grid grid-cols-1 md:grid-cols-2 lg:grid-cols-3 gap-6\">\n    <div class=\"bg-white rounded-lg shadow p-4\">\n      <h2 class=\"text-xl font-semibold mb-2\">Najnowsza Premiera Produktu</h2>\n      <p class=\"text-gray-700\">VOZOL ogłasza nową linię produktów z innowacyjnymi funkcjami.</p>\n      <div class=\"mt-4 text-sm text-gray-500\">Opublikowano 15 czerwca 2023</div>\n    </div>\n    <div class=\"bg-white rounded-lg shadow p-4\">\n      <h2 class=\"text-xl font-semibold mb-2\">Uznanie w Branży</h2>\n      <p class=\"text-gray-700\">VOZOL otrzymuje prestiżową nagrodę za innowacje technologiczne.</p>\n      <div class=\"mt-4 text-sm text-gray-500\">Opublikowano 28 maja 2023</div>\n    </div>\n    <div class=\"bg-white rounded-lg shadow p-4\">\n      <h2 class=\"text-xl font-semibold mb-2\">Ogłoszenie Partnerstwa</h2>\n      <p class=\"text-gray-700\">VOZOL nawiązuje współpracę z wiodącą firmą technologiczną, aby poszerzyć zasięg rynkowy.</p>\n      <div class=\"mt-4 text-sm text-gray-500\">Opublikowano 10 kwietnia 2023</div>\n    </div>\n  </div>\n</div>"
  }
}